gitprof/__init__.py
gitprof/__main__.py
gitprof/command_utils.py
gitprof/files.py
gitprof/os_utils.py
gitprof/ssh.py
gitprof/ux.py
gitprof/cli/__init__.py
gitprof/cli/clone.py
gitprof/cli/config.py
gitprof/cli/profile.py
gitprof/vcs/__init__.py
gitprof/vcs/github_utils.py
gitprof/vcs/services.py
gitprof-1.1.1.dist-info/LICENSE
gitprof-1.1.1.dist-info/METADATA
gitprof-1.1.1.dist-info/WHEEL
gitprof-1.1.1.dist-info/entry_points.txt
gitprof-1.1.1.dist-info/top_level.txt
gitprof-1.1.1.dist-info/RECORD
