Metadata-Version: 2.1
Name: gitprof
Version: 1.1.1
Summary: CLI tool which simplifies Git usage with multiple online accounts/services.
Home-page: https://github.com/CabbageDevelopment/gitprof
Author: Sam McCormack
Author-email: cabbagedevelopment@gmail.com
License: UNKNOWN
Project-URL: Source, https://github.com/CabbageDevelopment/gitprof
Keywords: git profiles github gitlab bitbucket cli tool accounts services
Platform: UNKNOWN
Classifier: Development Status :: 4 - Beta
Classifier: Intended Audience :: Developers
Classifier: License :: OSI Approved :: MIT License
Classifier: Programming Language :: Python :: 3.7
Classifier: Programming Language :: Python :: 3.8
Classifier: Programming Language :: Python :: 3.9
Requires-Python: ~=3.7
Requires-Dist: click (==7.1.2)
Requires-Dist: PyGithub (==1.53)
